bpcode/__init__.py
bpcode/backup.py
bpcode/bpdown.py
bpcode/cli.py
bpcode/nas.py
bpcode/startnas.py
bpcode/bpserver/__init__.py
bpcode/bpserver/manage.py
bpcode/bpserver/app01/__init__.py
bpcode/bpserver/app01/admin.py
bpcode/bpserver/app01/apps.py
bpcode/bpserver/app01/models.py
bpcode/bpserver/app01/tests.py
bpcode/bpserver/app01/views.py
bpcode/bpserver/app01/migrations/__init__.py
bpcode/bpserver/assets/Dir-D95qnDEz.js
bpcode/bpserver/assets/Dir-DdCaAE0_.css
bpcode/bpserver/assets/Doc-CYPfNYYT.js
bpcode/bpserver/assets/Doc-Cvapk1As.css
bpcode/bpserver/assets/File-C80CNSwJ.css
bpcode/bpserver/assets/File-qBywGu3U.js
bpcode/bpserver/assets/Home-BZwLJ2y2.js
bpcode/bpserver/assets/Home-C59lPf7-.css
bpcode/bpserver/assets/_plugin-vue_export-helper-DlAUqK2U.js
bpcode/bpserver/assets/index-DK1kuFPf.css
bpcode/bpserver/assets/index-z8FtxWqV.js
bpcode/bpserver/assets/store.svg
bpcode/bpserver/assets/vite.svg
bpcode/bpserver/assets/assets/Dir-D95qnDEz.js
bpcode/bpserver/assets/assets/Dir-DdCaAE0_.css
bpcode/bpserver/assets/assets/Doc-CYPfNYYT.js
bpcode/bpserver/assets/assets/Doc-Cvapk1As.css
bpcode/bpserver/assets/assets/File-C80CNSwJ.css
bpcode/bpserver/assets/assets/File-qBywGu3U.js
bpcode/bpserver/assets/assets/Home-BZwLJ2y2.js
bpcode/bpserver/assets/assets/Home-C59lPf7-.css
bpcode/bpserver/assets/assets/_plugin-vue_export-helper-DlAUqK2U.js
bpcode/bpserver/assets/assets/index-DK1kuFPf.css
bpcode/bpserver/assets/assets/index-z8FtxWqV.js
bpcode/bpserver/assets/assets/store.svg
bpcode/bpserver/assets/assets/vite.svg
bpcode/bpserver/bpserver/__init__.py
bpcode/bpserver/bpserver/asgi.py
bpcode/bpserver/bpserver/settings.py
bpcode/bpserver/bpserver/urls.py
bpcode/bpserver/bpserver/wsgi.py
bpcode/bpserver/code/version.json
bpcode/bpserver/logs/django_error.log
bpcode/bpserver/templates/index.html
bpcode-0.5.1.dist-info/METADATA
bpcode-0.5.1.dist-info/WHEEL
bpcode-0.5.1.dist-info/entry_points.txt
bpcode-0.5.1.dist-info/top_level.txt
bpcode-0.5.1.dist-info/RECORD
