Metadata-Version: 2.4
Name: bpcode
Version: 0.5.1
Summary: auto backup your code
Home-page: https://github.com/avegetableman/bpcode
Author: zhuoyue
Author-email: 2814401134@qq.com
Classifier: Programming Language :: Python :: 3
Classifier: License :: OSI Approved :: MIT License
Classifier: Operating System :: OS Independent
Requires-Python: >=3.6
Requires-Dist: django>=3.0
Requires-Dist: django-cors-headers
Requires-Dist: python-dotenv
Requires-Dist: whitenoise
Dynamic: author
Dynamic: author-email
Dynamic: classifier
Dynamic: description
Dynamic: description-content-type
Dynamic: home-page
Dynamic: requires-dist
Dynamic: requires-python
Dynamic: summary
